{"mc":{
	"pao":{
		"frameRate":60,
		"frames":[
			
			{
			"res":"F55EE557",
			"x":42,
			"y":6,
			"duration":4
			},
			{
			"res":"59E4DA2",
			"x":43,
			"y":8,
			"duration":4
			},
			{
			"res":"1BB158E9",
			"x":41,
			"y":6,
			"duration":4
			},
			{
			"res":"430325E0",
			"x":40,
			"y":5,
			"duration":4
			},
			{
			"res":"CC41A43A",
			"x":39,
			"y":5,
			"duration":4
			},
			{
			"res":"F07D8752",
			"x":41,
			"y":8,
			"duration":4
			},
			{
			"res":"23A97DCE",
			"x":42,
			"y":6,
			"duration":4
			}
			]
}},
	"res":{
		"F55EE557":{"x":0,"y":99,"w":97,"h":93},
		"59E4DA2":{"x":97,"y":96,"w":89,"h":96},
		"1BB158E9":{"x":186,"y":96,"w":84,"h":99},
		"430325E0":{"x":270,"y":0,"w":77,"h":100},
		"CC41A43A":{"x":187,"y":0,"w":83,"h":96},
		"F07D8752":{"x":96,"y":0,"w":91,"h":96},
		"23A97DCE":{"x":0,"y":0,"w":96,"h":99}
	}}